odoo/addons/analytic_tag_dimension_sale_warning/README.rst
odoo/addons/analytic_tag_dimension_sale_warning/__init__.py
odoo/addons/analytic_tag_dimension_sale_warning/__manifest__.py
odoo/addons/analytic_tag_dimension_sale_warning/i18n/analytic_tag_dimension_sale_warning.pot
odoo/addons/analytic_tag_dimension_sale_warning/i18n/ca.po
odoo/addons/analytic_tag_dimension_sale_warning/i18n/de.po
odoo/addons/analytic_tag_dimension_sale_warning/i18n/es.po
odoo/addons/analytic_tag_dimension_sale_warning/i18n/es_CO.po
odoo/addons/analytic_tag_dimension_sale_warning/i18n/fr.po
odoo/addons/analytic_tag_dimension_sale_warning/models/__init__.py
odoo/addons/analytic_tag_dimension_sale_warning/models/analytic.py
odoo/addons/analytic_tag_dimension_sale_warning/models/sale.py
odoo/addons/analytic_tag_dimension_sale_warning/readme/CONTRIBUTORS.rst
odoo/addons/analytic_tag_dimension_sale_warning/readme/DESCRIPTION.rst
odoo/addons/analytic_tag_dimension_sale_warning/readme/HISTORY.rst
odoo/addons/analytic_tag_dimension_sale_warning/readme/INSTALL.rst
odoo/addons/analytic_tag_dimension_sale_warning/static/description/icon.png
odoo/addons/analytic_tag_dimension_sale_warning/static/description/index.html
odoo13_addon_analytic_tag_dimension_sale_warning-13.0.1.0.1.dev10.dist-info/METADATA
odoo13_addon_analytic_tag_dimension_sale_warning-13.0.1.0.1.dev10.dist-info/WHEEL
odoo13_addon_analytic_tag_dimension_sale_warning-13.0.1.0.1.dev10.dist-info/top_level.txt
odoo13_addon_analytic_tag_dimension_sale_warning-13.0.1.0.1.dev10.dist-info/RECORD
